omorfi/__init__.py
omorfi/analyser.py
omorfi/analysis.py
omorfi/doc.py
omorfi/error_logging.py
omorfi/generator.py
omorfi/guesser.py
omorfi/hfst.py
omorfi/hyphenator.py
omorfi/labelsegmenter.py
omorfi/lemmatiser.py
omorfi/omorfi.py
omorfi/segmenter.py
omorfi/settings.py
omorfi/string_manglers.py
omorfi/token.py
omorfi/tokeniser.py
omorfi/disamparsulate/__init__.py
omorfi/disamparsulate/disamparsulator.py
omorfi/disamparsulate/evidence.py
omorfi/disamparsulate/matcher.py
omorfi/entryguessing/__init__.py
omorfi/entryguessing/gradation.py
omorfi/entryguessing/guess_feats.py
omorfi/entryguessing/guess_new_class.py
omorfi/entryguessing/parse_csv_data.py
omorfi/entryguessing/plurale_tantum.py
omorfi/entryguessing/stub.py
omorfi/entryguessing/wordmap.py
omorfi/formats/__init__.py
omorfi/formats/apertium_formatter.py
omorfi/formats/experimental_xml_formatter.py
omorfi/formats/fileformats.py
omorfi/formats/formatter.py
omorfi/formats/ftb3_formatter.py
omorfi/formats/giella_formatter.py
omorfi/formats/kotus_sanalista_formatter.py
omorfi/formats/labeled_segments_formatter.py
omorfi/formats/lexc_formatter.py
omorfi/formats/monodix_formatter.py
omorfi/formats/no_tags_formatter.py
omorfi/formats/omor_formatter.py
omorfi/formats/regex_formatter.py
omorfi/formats/tdt_formatter.py
omorfi/formats/twolc_formatter.py
omorfi-0.9.12.data/scripts/omorfi-conllu.py
omorfi-0.9.12.data/scripts/omorfi-convert.py
omorfi-0.9.12.data/scripts/omorfi-disamparsulate.py
omorfi-0.9.12.data/scripts/omorfi-download.py
omorfi-0.9.12.data/scripts/omorfi-factorise.py
omorfi-0.9.12.data/scripts/omorfi-freq-evals.py
omorfi-0.9.12.data/scripts/omorfi-ftb3.py
omorfi-0.9.12.data/scripts/omorfi-segment.py
omorfi-0.9.12.data/scripts/omorfi-sigmorphons.py
omorfi-0.9.12.data/scripts/omorfi-tokenise.py
omorfi-0.9.12.data/scripts/omorfi-unimorph.py
omorfi-0.9.12.data/scripts/omorfi-vislcg.py
omorfi-0.9.12.data/scripts/omorfi-wikitable.py
omorfi-0.9.12.dist-info/licenses/LICENSE
omorfi-0.9.12.dist-info/METADATA
omorfi-0.9.12.dist-info/WHEEL
omorfi-0.9.12.dist-info/top_level.txt
omorfi-0.9.12.dist-info/RECORD
