Metadata-Version: 2.4
Name: omorfi
Version: 0.9.12
Summary: Python bindings to omorfi
Home-page: https://github.com/flammie/omorfi
Author: Flammie A Pirinen
Author-email: Flammie A Pirinen <flammie@iki.fi>
License-Expression: GPL-3.0-only
Project-URL: homepage, https://flammie.github.io/omorfi/
Project-URL: repository, https://github.com/flammie/omorfi/
Keywords: finnish,nlp,morphology
Classifier: Programming Language :: Python :: 3
Classifier: Operating System :: OS Independent
Requires-Python: >=3.5
License-File: LICENSE
Requires-Dist: pyhfst
Dynamic: author
Dynamic: home-page
Dynamic: license-file
Dynamic: requires-python
